pineflow/core/__init__.py
pineflow/core/document/__init__.py
pineflow/core/document/schema.py
pineflow/core/embeddings/__init__.py
pineflow/core/embeddings/base.py
pineflow/core/evaluation/__init__.py
pineflow/core/evaluation/context_similarity.py
pineflow/core/flows/__init__.py
pineflow/core/flows/ingestion_flow.py
pineflow/core/llms/__init__.py
pineflow/core/llms/base.py
pineflow/core/llms/decorators.py
pineflow/core/llms/types.py
pineflow/core/monitors/__init__.py
pineflow/core/monitors/base.py
pineflow/core/monitors/types.py
pineflow/core/observability/__init__.py
pineflow/core/observability/base.py
pineflow/core/prompts/__init__.py
pineflow/core/prompts/base.py
pineflow/core/prompts/utils.py
pineflow/core/readers/__init__.py
pineflow/core/readers/base.py
pineflow/core/readers/directory.py
pineflow/core/text_chunkers/__init__.py
pineflow/core/text_chunkers/base.py
pineflow/core/text_chunkers/semantic.py
pineflow/core/text_chunkers/sentence.py
pineflow/core/text_chunkers/token.py
pineflow/core/text_chunkers/utils.py
pineflow/core/tools/__init__.py
pineflow/core/tools/base.py
pineflow/core/utils/pairwise.py
pineflow/core/vector_stores/__init__.py
pineflow/core/vector_stores/base.py
pineflow_core-0.7.9.dist-info/METADATA
pineflow_core-0.7.9.dist-info/WHEEL
pineflow_core-0.7.9.dist-info/RECORD
