Metadata-Version: 2.4
Name: pineflow-core
Version: 0.7.9
Summary: Load any data in one line of code and connect with AI applications
Project-URL: Documentation, https://run-pineflow.github.io/pineflow/
Project-URL: Repository, https://github.com/run-pineflow/pineflow
Author-email: Leonardo Furnielis <leonardofurnielis@outlook.com>
License: MIT
Keywords: AI,LLM,QA,RAG,data,monitor,retrieval,semantic-search
Classifier: Topic :: Scientific/Engineering :: Artificial Intelligence
Classifier: Topic :: Software Development :: Libraries :: Application Frameworks
Classifier: Topic :: Software Development :: Libraries :: Python Modules
Requires-Python: <4.0,>=3.10
Requires-Dist: deprecated<2.0.0,>=1.2.18
Requires-Dist: nltk<4.0.0,>=3.9.1
Requires-Dist: numpy<1.27.0,>=1.26.4
Requires-Dist: pydantic<3.0.0,>=2.11.5
Requires-Dist: tiktoken<0.10.0,>=0.9.0
Provides-Extra: dev
Requires-Dist: ruff>=0.11.13; extra == 'dev'
